klity/VERSION
klity/__init__.py
klity/klity.py
klity/main.py
klity/database/__init__.py
klity/database/postgresql.py
klity/features/__init__.py
klity/features/environment.py
klity/features/steps/__init__.py
klity/features/steps/steps_utils.py
klity/features/steps/steps_web.py
klity/features/steps/utils.py
klity/templates/default/index.html
klity/templates/default/static/bootstrap.bundle.min.js
klity/templates/default/static/bootstrap.min.css
klity/templates/default/static/bootstrap.min.js
klity/templates/default/static/jquery-3.4.1.min.js
klity/templates/default/static/style.css
k_lity-0.2.1.dist-info/LICENSE
k_lity-0.2.1.dist-info/METADATA
k_lity-0.2.1.dist-info/WHEEL
k_lity-0.2.1.dist-info/entry_points.txt
k_lity-0.2.1.dist-info/top_level.txt
k_lity-0.2.1.dist-info/RECORD
