Metadata-Version: 2.1
Name: k-lity
Version: 0.2.1
Summary: Tool made to ease testing websites
Home-page: https://framagit.org/Mindiell/k-lity
Author: Mindiell
License: GNU AFFERO GENERAL PUBLIC LICENSE version 3 or later
Project-URL: Documentation, https://k-lity.readthedocs.io/fr/latest/
Platform: UNKNOWN
Classifier: Development Status :: 3 - Alpha
Classifier: Environment :: Web Environment
Classifier: Intended Audience :: Developers
Classifier: License :: OSI Approved :: GNU Affero General Public License v3 or later (AGPLv3+)
Classifier: Operating System :: OS Independent
Classifier: Programming Language :: Python :: 3
Classifier: Programming Language :: Python :: 3.7
Classifier: Programming Language :: Python :: 3.8
Classifier: Programming Language :: Python :: 3.9
Classifier: Topic :: Software Development :: Testing
Requires-Python: >=3.7
Requires-Dist: behave (==1.2.6)
Requires-Dist: beautifulsoup4 (==4.9.3)
Requires-Dist: jinja2 (==2.11.3)
Requires-Dist: lxml (==4.6.2)
Requires-Dist: python-slugify (==4.0.1)
Requires-Dist: pyyaml (==5.4.1)
Requires-Dist: selenium (==3.141.0)
Provides-Extra: _
Requires-Dist: psycopg2-binary (==2.9.1) ; extra == '_'
Provides-Extra: postgresql
Requires-Dist: psycopg2-binary (==2.9.1) ; extra == 'postgresql'
Provides-Extra: test
Requires-Dist: pytest (==6.2.2) ; extra == 'test'
Requires-Dist: pytest-black (==0.3.12) ; extra == 'test'
Requires-Dist: pytest-isort (==2.0.0) ; extra == 'test'
